gitam/__init__.py
gitam/result.py
gitam-0.3.1.dist-info/LICENSE
gitam-0.3.1.dist-info/METADATA
gitam-0.3.1.dist-info/WHEEL
gitam-0.3.1.dist-info/top_level.txt
gitam-0.3.1.dist-info/RECORD
